LICENSE
MANIFEST.in
README.md
setup.py
a10_horizon/__init__.py
a10_horizon.egg-info/PKG-INFO
a10_horizon.egg-info/SOURCES.txt
a10_horizon.egg-info/dependency_links.txt
a10_horizon.egg-info/requires.txt
a10_horizon.egg-info/top_level.txt
a10_horizon/_enabled_hooks/_90000_a10networks_panel.py
a10_horizon/_enabled_hooks/_90010_a10ssl.py
a10_horizon/_enabled_hooks/_90020_a10appliances.py
a10_horizon/_enabled_hooks/_90100_a10scaling.py
a10_horizon/dashboard/__init__.py
a10_horizon/dashboard/base.py
a10_horizon/dashboard/a10networks/__init__.py
a10_horizon/dashboard/a10networks/urls.py
a10_horizon/dashboard/a10networks/views.py
a10_horizon/dashboard/a10networks/a10appliances/__init__.py
a10_horizon/dashboard/a10networks/a10appliances/forms.py
a10_horizon/dashboard/a10networks/a10appliances/panel.py
a10_horizon/dashboard/a10networks/a10appliances/tables.py
a10_horizon/dashboard/a10networks/a10appliances/tabs.py
a10_horizon/dashboard/a10networks/a10appliances/urls.py
a10_horizon/dashboard/a10networks/a10appliances/views.py
a10_horizon/dashboard/a10networks/a10appliances/workflows.py
a10_horizon/dashboard/a10networks/a10appliances/templates/_appliance_details.html
a10_horizon/dashboard/a10networks/a10appliances/templates/_create_appliance_help.html
a10_horizon/dashboard/a10networks/a10appliances/templates/_create_image_help.html
a10_horizon/dashboard/a10networks/a10appliances/templates/_update_appliance.html
a10_horizon/dashboard/a10networks/a10appliances/templates/_update_image.html
a10_horizon/dashboard/a10networks/a10appliances/templates/appliances_tabs.html
a10_horizon/dashboard/a10networks/a10appliances/templates/details_tabs.html
a10_horizon/dashboard/a10networks/a10appliances/templates/logo.html
a10_horizon/dashboard/a10networks/a10scaling/__init__.py
a10_horizon/dashboard/a10networks/a10scaling/constants.py
a10_horizon/dashboard/a10networks/a10scaling/forms.py
a10_horizon/dashboard/a10networks/a10scaling/panel.py
a10_horizon/dashboard/a10networks/a10scaling/tables.py
a10_horizon/dashboard/a10networks/a10scaling/tabs.py
a10_horizon/dashboard/a10networks/a10scaling/urls.py
a10_horizon/dashboard/a10networks/a10scaling/views.py
