Metadata-Version: 1.1
Name: a10-horizon
Version: 0.1.5
Summary: A10 Networks Openstack Horizon Dashboard
Home-page: https://github.com/a10networks/a10-horizon
Author: A10 Networks
Author-email: dougw@a10networks.com
License: Apache
Keywords: a10 adc slb load balancer openstack neutron lbaas horizon
Platform: UNKNOWN
Classifier: License :: OSI Approved :: Apache Software License
Classifier: Operating System :: POSIX
Classifier: Programming Language :: Python
Classifier: Programming Language :: Python :: 2.6
Classifier: Programming Language :: Python :: 2.7
Classifier: Topic :: Internet
